{
  "info": {
    "description": "data",
    "version": "1.0",
    "year": 2025,
    "contributor": "search engine",
    "source": "augmented",
    "license": {
      "name": "Creative Commons Attribution 4.0 International",
      "url": "https://creativecommons.org/licenses/by/4.0/"
    }
  },
  "images": [
    {
      "id": 6162171663,
      "width": 640,
      "height": 640,
      "file_name": "DSC_1261_17kv11r25k_3.jpg",
      "size": 72039,
      "format": "JPEG",
      "url": "",
      "hash": "",
      "status": "success"
    }
  ],
  "annotations": [
    {
      "id": 2759963663,
      "image_id": 6162171663,
      "category_id": 5111267663,
      "segmentation": [],
      "area": 2723.0590943232,
      "bbox": [
        72.39424,
        618.26688,
        62.64768,
        43.46624
      ]
    },
    {
      "id": 4450609663,
      "image_id": 6162171663,
      "category_id": 5111267663,
      "segmentation": [],
      "area": 3617.54781696,
      "bbox": [
        27.18848,
        284.96192,
        54.37632,
        66.528
      ]
    },
    {
      "id": 5719384663,
      "image_id": 6162171663,
      "category_id": 5111267663,
      "segmentation": [],
      "area": 2326.2042112,
      "bbox": [
        102.05311999999999,
        323.21599999999995,
        47.68,
        48.787839999999996
      ]
    },
    {
      "id": 2194257663,
      "image_id": 6162171663,
      "category_id": 5111267663,
      "segmentation": [],
      "area": 5152.4921229312,
      "bbox": [
        187.7088,
        288.84224,
        70.40832,
        73.18016
      ]
    },
    {
      "id": 6403582663,
      "image_id": 6162171663,
      "category_id": 5111267663,
      "segmentation": [],
      "area": 4169.6260784128,
      "bbox": [
        189.09568000000002,
        182.67392,
        63.201280000000004,
        65.97376
      ]
    },
    {
      "id": 3082882663,
      "image_id": 6162171663,
      "category_id": 5111267663,
      "segmentation": [],
      "area": 3551.7400940544,
      "bbox": [
        244.53632,
        230.90816,
        59.87392,
        59.32032
      ]
    },
    {
      "id": 7908236663,
      "image_id": 6162171663,
      "category_id": 5111267663,
      "segmentation": [],
      "area": 5354.1993414656,
      "bbox": [
        159.71071999999998,
        220.65215999999998,
        72.07168,
        74.28992
      ]
    },
    {
      "id": 4495525663,
      "image_id": 6162171663,
      "category_id": 5111267663,
      "segmentation": [],
      "area": 5074.3997825024,
      "bbox": [
        411.4112,
        467.63584000000003,
        72.07168,
        70.40768
      ]
    },
    {
      "id": 3248680663,
      "image_id": 6162171663,
      "category_id": 5111267663,
      "segmentation": [],
      "area": 3440.28094464,
      "bbox": [
        372.32511999999997,
        459.87584,
        50.44992,
        68.19200000000001
      ]
    },
    {
      "id": 8438875663,
      "image_id": 6162171663,
      "category_id": 5111267663,
      "segmentation": [],
      "area": 1913.30971648,
      "bbox": [
        36.06208,
        13.264,
        72.12416,
        26.528
      ]
    }
  ],
  "categories": [
    {
      "id": 5111267663,
      "name": "AppleBBCH81",
      "supercategory": "apple"
    }
  ]
}