{
  "info": {
    "description": "data",
    "version": "1.0",
    "year": 2025,
    "contributor": "search engine",
    "source": "augmented",
    "license": {
      "name": "Creative Commons Attribution 4.0 International",
      "url": "https://creativecommons.org/licenses/by/4.0/"
    }
  },
  "images": [
    {
      "id": 3768272002,
      "width": 640,
      "height": 640,
      "file_name": "DSC_1399_17kv39r4k_9.jpg",
      "size": 97063,
      "format": "JPEG",
      "url": "",
      "hash": "",
      "status": "success"
    }
  ],
  "annotations": [
    {
      "id": 7766336003,
      "image_id": 3768272002,
      "category_id": 3612340002,
      "segmentation": [],
      "area": 2351.8454784000005,
      "bbox": [
        85.80287999999999,
        586.94272,
        48.912000000000006,
        48.083200000000005
      ]
    },
    {
      "id": 3358528003,
      "image_id": 3768272002,
      "category_id": 3612340002,
      "segmentation": [],
      "area": 2946.9296099328,
      "bbox": [
        36.05888,
        93.96032,
        52.11392,
        56.54784
      ]
    },
    {
      "id": 3961137003,
      "image_id": 3768272002,
      "category_id": 3612340002,
      "segmentation": [],
      "area": 2715.5871834112,
      "bbox": [
        90.11264,
        150.78592,
        51.56032,
        52.66816
      ]
    },
    {
      "id": 5489095003,
      "image_id": 3768272002,
      "category_id": 3612340002,
      "segmentation": [],
      "area": 2201.0069401599994,
      "bbox": [
        97.31968,
        171.29791999999998,
        51.56032,
        42.687999999999995
      ]
    },
    {
      "id": 9020318003,
      "image_id": 3768272002,
      "category_id": 3612340002,
      "segmentation": [],
      "area": 2049.4592475136,
      "bbox": [
        449.08736,
        625.33056,
        69.85472,
        29.33888
      ]
    },
    {
      "id": 2669741003,
      "image_id": 3768272002,
      "category_id": 3612340002,
      "segmentation": [],
      "area": 3354.4721547264,
      "bbox": [
        484.28992,
        597.90976,
        59.32096,
        56.54784
      ]
    },
    {
      "id": 9383147003,
      "image_id": 3768272002,
      "category_id": 3612340002,
      "segmentation": [],
      "area": 2398.0741427200005,
      "bbox": [
        482.35008,
        450.16191999999995,
        52.11392,
        46.016000000000005
      ]
    },
    {
      "id": 5054748003,
      "image_id": 3768272002,
      "category_id": 3612340002,
      "segmentation": [],
      "area": 2844.945911808,
      "bbox": [
        449.08736,
        416.34432,
        57.6576,
        49.342079999999996
      ]
    },
    {
      "id": 2157935003,
      "image_id": 3768272002,
      "category_id": 3612340002,
      "segmentation": [],
      "area": 2444.7065444352,
      "bbox": [
        496.48767999999995,
        419.94816000000003,
        53.777280000000005,
        45.45984
      ]
    },
    {
      "id": 6133376003,
      "image_id": 3768272002,
      "category_id": 3612340002,
      "segmentation": [],
      "area": 3458.3904870400006,
      "bbox": [
        523.376,
        357.02207999999996,
        64.31104,
        53.776
      ]
    },
    {
      "id": 3931031003,
      "image_id": 3768272002,
      "category_id": 3612340002,
      "segmentation": [],
      "area": 3551.3162661888005,
      "bbox": [
        505.0816,
        340.38975999999997,
        58.767360000000004,
        60.430080000000004
      ]
    },
    {
      "id": 9385986003,
      "image_id": 3768272002,
      "category_id": 3612340002,
      "segmentation": [],
      "area": 2230.42277376,
      "bbox": [
        347.63072,
        16.48832,
        67.63776,
        32.976
      ]
    },
    {
      "id": 7794976003,
      "image_id": 3768272002,
      "category_id": 3612340002,
      "segmentation": [],
      "area": 715.8236839936001,
      "bbox": [
        311.31775999999996,
        8.17216,
        43.79648,
        16.34432
      ]
    },
    {
      "id": 5184669003,
      "image_id": 3768272002,
      "category_id": 3612340002,
      "segmentation": [],
      "area": 1892.0687386624002,
      "bbox": [
        298.56704,
        34.083839999999995,
        44.906240000000004,
        42.13376
      ]
    },
    {
      "id": 4564574003,
      "image_id": 3768272002,
      "category_id": 3612340002,
      "segmentation": [],
      "area": 1770.3615283200002,
      "bbox": [
        326.56255999999996,
        42.400000000000006,
        39.91616,
        44.352000000000004
      ]
    },
    {
      "id": 4902979003,
      "image_id": 3768272002,
      "category_id": 3612340002,
      "segmentation": [],
      "area": 2561.5118778367996,
      "bbox": [
        254.67776,
        81.95584,
        51.73952,
        49.507839999999995
      ]
    },
    {
      "id": 5358523003,
      "image_id": 3768272002,
      "category_id": 3612340002,
      "segmentation": [],
      "area": 1380.7347499008001,
      "bbox": [
        259.06752,
        367.66848000000005,
        33.989760000000004,
        40.62208
      ]
    },
    {
      "id": 7404467003,
      "image_id": 3768272002,
      "category_id": 3612340002,
      "segmentation": [],
      "area": 876.96063488,
      "bbox": [
        224.24896,
        367.25375999999994,
        24.041600000000003,
        36.4768
      ]
    },
    {
      "id": 9441592003,
      "image_id": 3768272002,
      "category_id": 3612340002,
      "segmentation": [],
      "area": 1156.6638088192,
      "bbox": [
        446.42496,
        145.49248,
        27.35744,
        42.27968
      ]
    },
    {
      "id": 1456051003,
      "image_id": 3768272002,
      "category_id": 3612340002,
      "segmentation": [],
      "area": 2193.7539178496004,
      "bbox": [
        421.96864,
        105.69919999999999,
        46.424960000000006,
        47.25376
      ]
    },
    {
      "id": 7286971003,
      "image_id": 3768272002,
      "category_id": 3612340002,
      "segmentation": [],
      "area": 569.0602192896,
      "bbox": [
        424.8704,
        208.912,
        19.067520000000002,
        29.84448
      ]
    },
    {
      "id": 3871159003,
      "image_id": 3768272002,
      "category_id": 3612340002,
      "segmentation": [],
      "area": 831.5864137727999,
      "bbox": [
        501.96864,
        630.8806400000001,
        45.59616,
        18.23808
      ]
    }
  ],
  "categories": [
    {
      "id": 3612340002,
      "name": "AppleBBCH81",
      "supercategory": "apple"
    }
  ]
}