{
  "info": {
    "description": "data",
    "version": "1.0",
    "year": 2025,
    "contributor": "search engine",
    "source": "augmented",
    "license": {
      "name": "Creative Commons Attribution 4.0 International",
      "url": "https://creativecommons.org/licenses/by/4.0/"
    }
  },
  "images": [
    {
      "id": 2942706137,
      "width": 640,
      "height": 640,
      "file_name": "DSC_1311_17kv13r28k_7.jpg",
      "size": 115296,
      "format": "JPEG",
      "url": "",
      "hash": "",
      "status": "success"
    }
  ],
  "annotations": [
    {
      "id": 1737341137,
      "image_id": 2942706137,
      "category_id": 9485136137,
      "segmentation": [],
      "area": 3311.4853474304,
      "bbox": [
        211.81568,
        621.45024,
        89.25952000000001,
        37.09952
      ]
    },
    {
      "id": 4786097137,
      "image_id": 2942706137,
      "category_id": 9485136137,
      "segmentation": [],
      "area": 3887.9681708032,
      "bbox": [
        140.2976,
        560.76608,
        63.754239999999996,
        60.98368
      ]
    },
    {
      "id": 5881442137,
      "image_id": 2942706137,
      "category_id": 9485136137,
      "segmentation": [],
      "area": 4171.471298560001,
      "bbox": [
        191.02464,
        488.416,
        64.31104,
        64.864
      ]
    },
    {
      "id": 9440135137,
      "image_id": 2942706137,
      "category_id": 9485136137,
      "segmentation": [],
      "area": 3779.3077215232006,
      "bbox": [
        391.1616,
        426.04607999999996,
        64.31104,
        58.76608
      ]
    },
    {
      "id": 6479106137,
      "image_id": 2942706137,
      "category_id": 9485136137,
      "segmentation": [],
      "area": 5020.978013798401,
      "bbox": [
        424.04159999999996,
        522.19904,
        67.15008,
        74.77248
      ]
    },
    {
      "id": 1360461137,
      "image_id": 2942706137,
      "category_id": 9485136137,
      "segmentation": [],
      "area": 3644.0710225919997,
      "bbox": [
        565.80032,
        413.84832000000006,
        57.6576,
        63.201919999999994
      ]
    },
    {
      "id": 8829093137,
      "image_id": 2942706137,
      "category_id": 9485136137,
      "segmentation": [],
      "area": 3708.061378969601,
      "bbox": [
        550.82944,
        333.45984,
        64.31104,
        57.658240000000006
      ]
    },
    {
      "id": 9491227137,
      "image_id": 2942706137,
      "category_id": 9485136137,
      "segmentation": [],
      "area": 4996.4898164736,
      "bbox": [
        401.1424,
        262.77376,
        70.96448,
        70.40832
      ]
    },
    {
      "id": 9600800137,
      "image_id": 2942706137,
      "category_id": 9485136137,
      "segmentation": [],
      "area": 3819.2584065024007,
      "bbox": [
        380.07424000000003,
        32.144,
        63.201280000000004,
        60.430080000000004
      ]
    },
    {
      "id": 8176390137,
      "image_id": 2942706137,
      "category_id": 9485136137,
      "segmentation": [],
      "area": 1897.7946107904,
      "bbox": [
        434.92096,
        43.523199999999996,
        48.70656,
        38.96384
      ]
    },
    {
      "id": 3859158137,
      "image_id": 2942706137,
      "category_id": 9485136137,
      "segmentation": [],
      "area": 573.08416,
      "bbox": [
        631.7280000000001,
        17.32032,
        16.544,
        34.64
      ]
    },
    {
      "id": 3644379137,
      "image_id": 2942706137,
      "category_id": 9485136137,
      "segmentation": [],
      "area": 2369.5078694911995,
      "bbox": [
        32.02496,
        578.22784,
        54.101119999999995,
        43.79776
      ]
    },
    {
      "id": 9539424137,
      "image_id": 2942706137,
      "category_id": 9485136137,
      "segmentation": [],
      "area": 3069.354528768,
      "bbox": [
        478.34176,
        525.18144,
        48.083200000000005,
        63.834239999999994
      ]
    },
    {
      "id": 7721799137,
      "image_id": 2942706137,
      "category_id": 9485136137,
      "segmentation": [],
      "area": 2655.5968479232006,
      "bbox": [
        507.77216000000004,
        597.72032,
        57.20192,
        46.424960000000006
      ]
    },
    {
      "id": 3722224137,
      "image_id": 2942706137,
      "category_id": 9485136137,
      "segmentation": [],
      "area": 1913.3574676480002,
      "bbox": [
        620.1036799999999,
        556.26944,
        39.79264,
        48.083200000000005
      ]
    },
    {
      "id": 1819872137,
      "image_id": 2942706137,
      "category_id": 9485136137,
      "segmentation": [],
      "area": 3856.9638854656,
      "bbox": [
        254.09344000000002,
        533.05728,
        50.57024,
        76.26944
      ]
    },
    {
      "id": 7253977137,
      "image_id": 2942706137,
      "category_id": 9485136137,
      "segmentation": [],
      "area": 1865.2297728,
      "bbox": [
        193.98976000000002,
        545.07776,
        38.1344,
        48.912000000000006
      ]
    },
    {
      "id": 8115499137,
      "image_id": 2942706137,
      "category_id": 9485136137,
      "segmentation": [],
      "area": 1477.6144416768002,
      "bbox": [
        343.21216,
        17.823999999999998,
        41.450880000000005,
        35.64736
      ]
    },
    {
      "id": 4395134137,
      "image_id": 2942706137,
      "category_id": 9485136137,
      "segmentation": [],
      "area": 2903.7096177663993,
      "bbox": [
        507.77216000000004,
        31.9168,
        53.88607999999999,
        53.88607999999999
      ]
    },
    {
      "id": 7219153137,
      "image_id": 2942706137,
      "category_id": 9485136137,
      "segmentation": [],
      "area": 1962.8324528128003,
      "bbox": [
        569.53344,
        285.59616,
        46.424960000000006,
        42.27968
      ]
    }
  ],
  "categories": [
    {
      "id": 9485136137,
      "name": "AppleBBCH81",
      "supercategory": "apple"
    }
  ]
}