{
  "info": {
    "description": "data",
    "version": "1.0",
    "year": 2025,
    "contributor": "search engine",
    "source": "augmented",
    "license": {
      "name": "Creative Commons Attribution 4.0 International",
      "url": "https://creativecommons.org/licenses/by/4.0/"
    }
  },
  "images": [
    {
      "id": 5151896275,
      "width": 640,
      "height": 640,
      "file_name": "DSC_1164_17kv7r28k_5.jpg",
      "size": 89799,
      "format": "JPEG",
      "url": "",
      "hash": "",
      "status": "success"
    }
  ],
  "annotations": [
    {
      "id": 7647004276,
      "image_id": 5151896275,
      "category_id": 9314988275,
      "segmentation": [],
      "area": 4306.564659609599,
      "bbox": [
        610.48448,
        76.53376,
        59.03104,
        72.95424
      ]
    },
    {
      "id": 6956582276,
      "image_id": 5151896275,
      "category_id": 9314988275,
      "segmentation": [],
      "area": 3484.2744381439998,
      "bbox": [
        548.93952,
        24.4768,
        71.17504,
        48.9536
      ]
    },
    {
      "id": 8224670276,
      "image_id": 5151896275,
      "category_id": 9314988275,
      "segmentation": [],
      "area": 6729.6803422207995,
      "bbox": [
        467.56480000000005,
        124.35264000000001,
        84.55936,
        79.58528
      ]
    },
    {
      "id": 9809843276,
      "image_id": 5151896275,
      "category_id": 9314988275,
      "segmentation": [],
      "area": 2571.9526088704,
      "bbox": [
        385.82079999999996,
        208.67007999999998,
        47.42528,
        54.231680000000004
      ]
    },
    {
      "id": 1380308276,
      "image_id": 5151896275,
      "category_id": 9314988275,
      "segmentation": [],
      "area": 3558.5521926144,
      "bbox": [
        368.39104,
        225.15968,
        62.38976,
        57.037440000000004
      ]
    },
    {
      "id": 8035319276,
      "image_id": 5151896275,
      "category_id": 9314988275,
      "segmentation": [],
      "area": 2734.4228941824003,
      "bbox": [
        27.39072,
        33.82976,
        52.990719999999996,
        51.60192000000001
      ]
    },
    {
      "id": 3851349276,
      "image_id": 5151896275,
      "category_id": 9314988275,
      "segmentation": [],
      "area": 2393.6280969216,
      "bbox": [
        275.80736,
        502.68992,
        48.04352,
        49.82208
      ]
    },
    {
      "id": 7134534276,
      "image_id": 5151896275,
      "category_id": 9314988275,
      "segmentation": [],
      "area": 2815.6849659904005,
      "bbox": [
        372.70848,
        576.16576,
        60.650240000000004,
        46.424960000000006
      ]
    },
    {
      "id": 7905358276,
      "image_id": 5151896275,
      "category_id": 9314988275,
      "segmentation": [],
      "area": 1429.4899302399997,
      "bbox": [
        38.54912,
        13.264,
        53.88607999999999,
        26.528
      ]
    }
  ],
  "categories": [
    {
      "id": 9314988275,
      "name": "AppleBBCH81",
      "supercategory": "apple"
    }
  ]
}