{
  "info": {
    "description": "data",
    "version": "1.0",
    "year": 2025,
    "contributor": "search engine",
    "source": "augmented",
    "license": {
      "name": "Creative Commons Attribution 4.0 International",
      "url": "https://creativecommons.org/licenses/by/4.0/"
    }
  },
  "images": [
    {
      "id": 5321754993,
      "width": 640,
      "height": 640,
      "file_name": "DSC_1210_17kv10r30k_0.jpg",
      "size": 96680,
      "format": "JPEG",
      "url": "",
      "hash": "",
      "status": "success"
    }
  ],
  "annotations": [
    {
      "id": 1984834994,
      "image_id": 5321754993,
      "category_id": 1783289993,
      "segmentation": [],
      "area": 3502.7328106496,
      "bbox": [
        612.64256,
        153.04512,
        54.71488,
        64.01792
      ]
    },
    {
      "id": 8515428994,
      "image_id": 5321754993,
      "category_id": 1783289993,
      "segmentation": [],
      "area": 8465.0789339136,
      "bbox": [
        380.10368,
        82.48704000000001,
        93.67872,
        90.36288
      ]
    },
    {
      "id": 9766289994,
      "image_id": 5321754993,
      "category_id": 1783289993,
      "segmentation": [],
      "area": 5049.140150271999,
      "bbox": [
        550.33536,
        286.56768,
        74.8736,
        67.43552
      ]
    },
    {
      "id": 8645695994,
      "image_id": 5321754993,
      "category_id": 1783289993,
      "segmentation": [],
      "area": 8641.6196419584,
      "bbox": [
        445.19104,
        361.94687999999996,
        99.46176,
        86.88383999999999
      ]
    },
    {
      "id": 5203334994,
      "image_id": 5321754993,
      "category_id": 1783289993,
      "segmentation": [],
      "area": 9087.715786752002,
      "bbox": [
        517.3055999999999,
        483.13536,
        89.53344,
        101.50080000000001
      ]
    },
    {
      "id": 1337101994,
      "image_id": 5321754993,
      "category_id": 1783289993,
      "segmentation": [],
      "area": 6620.346886553599,
      "bbox": [
        383.89311999999995,
        250.0,
        72.95295999999999,
        90.74816
      ]
    },
    {
      "id": 7825725994,
      "image_id": 5321754993,
      "category_id": 1783289993,
      "segmentation": [],
      "area": 9179.582196940799,
      "bbox": [
        253.264,
        242.88191999999998,
        105.28511999999999,
        87.18784
      ]
    },
    {
      "id": 9288924994,
      "image_id": 5321754993,
      "category_id": 1783289993,
      "segmentation": [],
      "area": 7859.3307107328,
      "bbox": [
        271.90656,
        329.82784000000004,
        94.52928,
        83.14176
      ]
    },
    {
      "id": 7993374994,
      "image_id": 5321754993,
      "category_id": 1783289993,
      "segmentation": [],
      "area": 7950.8056051712,
      "bbox": [
        114.40384,
        269.57184,
        91.19168,
        87.18784
      ]
    },
    {
      "id": 6427381994,
      "image_id": 5321754993,
      "category_id": 1783289993,
      "segmentation": [],
      "area": 8797.121380352,
      "bbox": [
        47.3728,
        192.33152,
        94.7456,
        92.84992000000001
      ]
    },
    {
      "id": 5973733994,
      "image_id": 5321754993,
      "category_id": 1783289993,
      "segmentation": [],
      "area": 9542.181963776,
      "bbox": [
        58.69632,
        447.06304,
        104.12864,
        91.6384
      ]
    },
    {
      "id": 7145046994,
      "image_id": 5321754993,
      "category_id": 1783289993,
      "segmentation": [],
      "area": 8560.270728396801,
      "bbox": [
        138.03136,
        524.39488,
        118.54912,
        72.20864
      ]
    },
    {
      "id": 2977268994,
      "image_id": 5321754993,
      "category_id": 1783289993,
      "segmentation": [],
      "area": 3487.1986483200008,
      "bbox": [
        356.06208000000004,
        165.80288,
        48.912000000000006,
        71.29536
      ]
    },
    {
      "id": 2558346994,
      "image_id": 5321754993,
      "category_id": 1783289993,
      "segmentation": [],
      "area": 3900.8820494336,
      "bbox": [
        27.35744,
        604.35264,
        54.71488,
        71.29472
      ]
    }
  ],
  "categories": [
    {
      "id": 1783289993,
      "name": "AppleBBCH81",
      "supercategory": "apple"
    }
  ]
}