{
  "info": {
    "description": "data",
    "version": "1.0",
    "year": 2025,
    "contributor": "search engine",
    "source": "augmented",
    "license": {
      "name": "Creative Commons Attribution 4.0 International",
      "url": "https://creativecommons.org/licenses/by/4.0/"
    }
  },
  "images": [
    {
      "id": 3699132371,
      "width": 640,
      "height": 640,
      "file_name": "DSC_1043_17kv1r17k_12.jpg",
      "size": 94683,
      "format": "JPEG",
      "url": "",
      "hash": "",
      "status": "success"
    }
  ],
  "annotations": [
    {
      "id": 3517811372,
      "image_id": 3699132371,
      "category_id": 9599346371,
      "segmentation": [],
      "area": 448.53443379199996,
      "bbox": [
        512.95104,
        3.71264,
        60.4064,
        7.42528
      ]
    },
    {
      "id": 9541710372,
      "image_id": 3699132371,
      "category_id": 9599346371,
      "segmentation": [],
      "area": 2709.7891209216004,
      "bbox": [
        141.18912,
        22.670080000000002,
        59.76576,
        45.340160000000004
      ]
    },
    {
      "id": 2868374372,
      "image_id": 3699132371,
      "category_id": 9599346371,
      "segmentation": [],
      "area": 10306.106457292799,
      "bbox": [
        45.048959999999994,
        77.47200000000001,
        90.09791999999999,
        114.38784
      ]
    },
    {
      "id": 8331434372,
      "image_id": 3699132371,
      "category_id": 9599346371,
      "segmentation": [],
      "area": 2061.5751364608,
      "bbox": [
        264.89664,
        105.10400000000001,
        50.12544,
        41.12832
      ]
    },
    {
      "id": 9527364372,
      "image_id": 3699132371,
      "category_id": 9599346371,
      "segmentation": [],
      "area": 3843.0455029759996,
      "bbox": [
        318.23424,
        146.55424,
        60.4064,
        63.619839999999996
      ]
    },
    {
      "id": 4773841372,
      "image_id": 3699132371,
      "category_id": 9599346371,
      "segmentation": [],
      "area": 3457.3742055424,
      "bbox": [
        279.9968,
        189.93216,
        58.478719999999996,
        59.12192
      ]
    },
    {
      "id": 8718696372,
      "image_id": 3699132371,
      "category_id": 9599346371,
      "segmentation": [],
      "area": 2197.0798415872005,
      "bbox": [
        289.95904,
        259.33632,
        44.98496,
        48.840320000000006
      ]
    },
    {
      "id": 1635562372,
      "image_id": 3699132371,
      "category_id": 9599346371,
      "segmentation": [],
      "area": 6608.4683440128,
      "bbox": [
        208.34304,
        266.72576,
        80.97216,
        81.61408
      ]
    },
    {
      "id": 8204307372,
      "image_id": 3699132371,
      "category_id": 9599346371,
      "segmentation": [],
      "area": 3390.9172600832,
      "bbox": [
        201.59616,
        304.64192,
        76.47232,
        44.34176
      ]
    },
    {
      "id": 9592434372,
      "image_id": 3699132371,
      "category_id": 9599346371,
      "segmentation": [],
      "area": 2702.8829183999997,
      "bbox": [
        339.76256,
        451.80416,
        49.4816,
        54.623999999999995
      ]
    },
    {
      "id": 4409171372,
      "image_id": 3699132371,
      "category_id": 9599346371,
      "segmentation": [],
      "area": 6759.5421089792,
      "bbox": [
        276.46208,
        488.75584000000003,
        79.68512,
        84.82816
      ]
    },
    {
      "id": 8268042372,
      "image_id": 3699132371,
      "category_id": 9599346371,
      "segmentation": [],
      "area": 1536.3019702272002,
      "bbox": [
        214.12735999999998,
        450.83968,
        39.84384,
        38.558080000000004
      ]
    },
    {
      "id": 1573204372,
      "image_id": 3699132371,
      "category_id": 9599346371,
      "segmentation": [],
      "area": 11338.70314496,
      "bbox": [
        178.78336000000002,
        544.66624,
        113.104,
        100.25024
      ]
    },
    {
      "id": 3310757372,
      "image_id": 3699132371,
      "category_id": 9599346371,
      "segmentation": [],
      "area": 3888.6563856383996,
      "bbox": [
        114.83904000000001,
        425.13599999999997,
        68.76288,
        56.55168
      ]
    },
    {
      "id": 5281535372,
      "image_id": 3699132371,
      "category_id": 9599346371,
      "segmentation": [],
      "area": 5110.545604607999,
      "bbox": [
        84.63616,
        517.99616,
        63.61919999999999,
        80.33023999999999
      ]
    },
    {
      "id": 8961972372,
      "image_id": 3699132371,
      "category_id": 9599346371,
      "segmentation": [],
      "area": 1362.6667499520001,
      "bbox": [
        9.3824,
        537.27424,
        18.7648,
        72.61824
      ]
    },
    {
      "id": 2208364372,
      "image_id": 3699132371,
      "category_id": 9599346371,
      "segmentation": [],
      "area": 4573.6791597056,
      "bbox": [
        28.02048,
        595.75424,
        56.04032,
        81.61408
      ]
    },
    {
      "id": 5684710372,
      "image_id": 3699132371,
      "category_id": 9599346371,
      "segmentation": [],
      "area": 1268.3057643519999,
      "bbox": [
        630.7776,
        600.896,
        18.4448,
        68.76223999999999
      ]
    },
    {
      "id": 1828416372,
      "image_id": 3699132371,
      "category_id": 9599346371,
      "segmentation": [],
      "area": 2047.4540236799999,
      "bbox": [
        608.7046399999999,
        496.78976,
        47.55328,
        43.056
      ]
    },
    {
      "id": 7143397372,
      "image_id": 3699132371,
      "category_id": 9599346371,
      "segmentation": [],
      "area": 878.3454928896001,
      "bbox": [
        633.02656,
        457.26784000000004,
        13.94688,
        62.977920000000005
      ]
    },
    {
      "id": 2567744372,
      "image_id": 3699132371,
      "category_id": 9599346371,
      "segmentation": [],
      "area": 1691.5387060224002,
      "bbox": [
        594.56384,
        301.74976000000004,
        41.12832,
        41.12832
      ]
    },
    {
      "id": 8159890372,
      "image_id": 3699132371,
      "category_id": 9599346371,
      "segmentation": [],
      "area": 2102.1445013504003,
      "bbox": [
        624.99456,
        68.79616,
        30.01088,
        70.04608
      ]
    }
  ],
  "categories": [
    {
      "id": 9599346371,
      "name": "AppleBBCH81",
      "supercategory": "apple"
    }
  ]
}