{
  "info": {
    "description": "data",
    "version": "1.0",
    "year": 2025,
    "contributor": "search engine",
    "source": "augmented",
    "license": {
      "name": "Creative Commons Attribution 4.0 International",
      "url": "https://creativecommons.org/licenses/by/4.0/"
    }
  },
  "images": [
    {
      "id": 2423298674,
      "width": 640,
      "height": 640,
      "file_name": "DSC_1371_17kv37r6k_2.jpg",
      "size": 112964,
      "format": "JPEG",
      "url": "",
      "hash": "",
      "status": "success"
    }
  ],
  "annotations": [
    {
      "id": 7125673675,
      "image_id": 2423298674,
      "category_id": 2945011674,
      "segmentation": [],
      "area": 2744.4632985600006,
      "bbox": [
        618.84416,
        573.50592,
        42.311040000000006,
        64.864
      ]
    },
    {
      "id": 4323368675,
      "image_id": 2423298674,
      "category_id": 2945011674,
      "segmentation": [],
      "area": 3954.09555456,
      "bbox": [
        610.528,
        516.40192,
        58.944,
        67.08224
      ]
    }
  ],
  "categories": [
    {
      "id": 2945011674,
      "name": "AppleBBCH81",
      "supercategory": "apple"
    }
  ]
}