{
  "info": {
    "description": "data",
    "version": "1.0",
    "year": 2025,
    "contributor": "search engine",
    "source": "augmented",
    "license": {
      "name": "Creative Commons Attribution 4.0 International",
      "url": "https://creativecommons.org/licenses/by/4.0/"
    }
  },
  "images": [
    {
      "id": 1591954951,
      "width": 640,
      "height": 640,
      "file_name": "DSC_1209_17kv10r29k_11.jpg",
      "size": 103610,
      "format": "JPEG",
      "url": "",
      "hash": "",
      "status": "success"
    }
  ],
  "annotations": [
    {
      "id": 8017913952,
      "image_id": 1591954951,
      "category_id": 2551117951,
      "segmentation": [],
      "area": 3912.335425536,
      "bbox": [
        609.7408,
        562.89344,
        60.5184,
        64.64704
      ]
    },
    {
      "id": 1292590952,
      "image_id": 1591954951,
      "category_id": 2551117951,
      "segmentation": [],
      "area": 3129.7961885696,
      "bbox": [
        476.26944000000003,
        552.12416,
        57.20192,
        54.71488
      ]
    },
    {
      "id": 2464037952,
      "image_id": 1591954951,
      "category_id": 2551117951,
      "segmentation": [],
      "area": 2012.3233550336,
      "bbox": [
        516.06208,
        591.9168,
        50.57024,
        39.79264
      ]
    },
    {
      "id": 2068807952,
      "image_id": 1591954951,
      "category_id": 2551117951,
      "segmentation": [],
      "area": 3853.6207265792,
      "bbox": [
        295.40288,
        353.3952,
        64.05824,
        60.15808
      ]
    },
    {
      "id": 3523189952,
      "image_id": 1591954951,
      "category_id": 2551117951,
      "segmentation": [],
      "area": 3304.2885500928005,
      "bbox": [
        239.35168000000002,
        358.1344,
        62.27776,
        53.057280000000006
      ]
    },
    {
      "id": 8763750952,
      "image_id": 1591954951,
      "category_id": 2551117951,
      "segmentation": [],
      "area": 5347.7997146112,
      "bbox": [
        171.61088,
        433.81952,
        76.26048,
        70.12544
      ]
    },
    {
      "id": 6864053952,
      "image_id": 1591954951,
      "category_id": 2551117951,
      "segmentation": [],
      "area": 9745.272299519998,
      "bbox": [
        236.68352,
        576.53376,
        96.08447999999999,
        101.424
      ]
    },
    {
      "id": 6480311952,
      "image_id": 1591954951,
      "category_id": 2551117951,
      "segmentation": [],
      "area": 3615.47968512,
      "bbox": [
        392.53888000000006,
        562.01344,
        62.176,
        58.149119999999996
      ]
    },
    {
      "id": 7554331952,
      "image_id": 1591954951,
      "category_id": 2551117951,
      "segmentation": [],
      "area": 4602.3755415552005,
      "bbox": [
        28.186239999999998,
        412.048,
        56.372479999999996,
        81.64224000000002
      ]
    },
    {
      "id": 7421076952,
      "image_id": 1591954951,
      "category_id": 2551117951,
      "segmentation": [],
      "area": 1387.0628868095998,
      "bbox": [
        9.11936,
        510.78144000000003,
        18.23808,
        76.05311999999999
      ]
    },
    {
      "id": 7141046952,
      "image_id": 1591954951,
      "category_id": 2551117951,
      "segmentation": [],
      "area": 7741.460744192,
      "bbox": [
        70.52672,
        597.8112,
        101.26016,
        76.4512
      ]
    }
  ],
  "categories": [
    {
      "id": 2551117951,
      "name": "AppleBBCH81",
      "supercategory": "apple"
    }
  ]
}